pyclassstruct/__init__.py
pyclassstruct/__main__.py
pyclassstruct/cli.py
pyclassstruct/analyzer/__init__.py
pyclassstruct/analyzer/ast_parser.py
pyclassstruct/analyzer/dependency.py
pyclassstruct/analyzer/keyword_matcher.py
pyclassstruct/analyzer/keywords.json
pyclassstruct/analyzer/models.py
pyclassstruct/generator/__init__.py
pyclassstruct/generator/class_builder.py
pyclassstruct/generator/naming.py
pyclassstruct/generator/structure.py
pyclassstruct/reporter/__init__.py
pyclassstruct/reporter/report.py
pyclassstruct/utils/__init__.py
pyclassstruct/utils/file_ops.py
pyclassstruct-1.0.1.dist-info/licenses/LICENSE
pyclassstruct-1.0.1.dist-info/METADATA
pyclassstruct-1.0.1.dist-info/WHEEL
pyclassstruct-1.0.1.dist-info/entry_points.txt
pyclassstruct-1.0.1.dist-info/top_level.txt
pyclassstruct-1.0.1.dist-info/RECORD
