Metadata-Version: 2.4
Name: pyclassstruct
Version: 1.0.1
Summary: Convert simple Python scripts to class-based structured code
Author: Mirjan Ali Sha
License: MIT
Project-URL: Homepage, https://github.com/Mirjan-Ali-Sha/pyclassstruct
Project-URL: Repository, https://github.com/Mirjan-Ali-Sha/pyclassstruct
Project-URL: Issues, https://github.com/Mirjan-Ali-Sha/pyclassstruct/issues
Keywords: python,refactoring,classes,structure,cli
Classifier: Development Status :: 4 - Beta
Classifier: Intended Audience :: Developers
Classifier: License :: OSI Approved :: MIT License
Classifier: Programming Language :: Python :: 3
Classifier: Programming Language :: Python :: 3.8
Classifier: Programming Language :: Python :: 3.9
Classifier: Programming Language :: Python :: 3.10
Classifier: Programming Language :: Python :: 3.11
Classifier: Programming Language :: Python :: 3.12
Classifier: Topic :: Software Development :: Code Generators
Requires-Python: >=3.8
License-File: LICENSE
Requires-Dist: click>=8.0.0
Provides-Extra: dev
Requires-Dist: pytest>=7.0.0; extra == "dev"
Dynamic: license-file
